zoombot/__init__.py
zoombot/core.py
zoombot/utils.py
zoombot-0.1.2.dist-info/LICENSE
zoombot-0.1.2.dist-info/WHEEL
zoombot-0.1.2.dist-info/METADATA
zoombot-0.1.2.dist-info/RECORD
